[  {"hanzi":"词", "pinyin":"cí", "ja":"言葉", "juzi_ch":"这是一个词。", "juzi_ja":"これは単語です。"},  {"hanzi":"书", "pinyin":"shū", "ja":"本", "juzi_ch":"我在读书。", "juzi_ja":"私は本を読んでいます。"},  {"hanzi":"老师", "pinyin":"lǎoshī", "ja":"先生", "juzi_ch":"老师教我们。", "juzi_ja":"先生は私たちを教えています。"},  {"hanzi":"学生", "pinyin":"xuéshēng", "ja":"学生", "juzi_ch":"他是学生。", "juzi_ja":"彼は学生です。"},  {"hanzi":"家", "pinyin":"jiā", "ja":"家", "juzi_ch":"我回家。", "juzi_ja":"私は家に帰ります。"},  {"hanzi":"水", "pinyin":"shuǐ", "ja":"水", "juzi_ch":"我喝水。", "juzi_ja":"私は水を飲みます。"} ]